AQAInterpreter/__init__.py
AQAInterpreter/__main__.py
AQAInterpreter/environment.py
AQAInterpreter/errors.py
AQAInterpreter/interpreter.py
AQAInterpreter/main.py
AQAInterpreter/parser.py
AQAInterpreter/scanner.py
AQAInterpreter/test_.py
AQAInterpreter/tokens.py
aqainterpreter-0.0.10.dist-info/METADATA
aqainterpreter-0.0.10.dist-info/WHEEL
aqainterpreter-0.0.10.dist-info/licenses/LICENSE
aqainterpreter-0.0.10.dist-info/RECORD
