Metadata-Version: 2.1
Name: AQAInterpreter
Version: 0.0.10
Project-URL: Documentation, https://github.com/CyberWarrior5466/nea
Project-URL: Issues, https://github.com/CyberWarrior5466/nea/issues
Project-URL: Source, https://github.com/CyberWarrior5466/nea
Author-email: CyberWarrior5466 <asaleen898@gmail.com>
License-Expression: MIT
License-File: LICENSE
Requires-Python: >=3.10
Requires-Dist: click==8.*
